iomeval/__init__.py
iomeval/_modidx.py
iomeval/core.py
iomeval/downloaders.py
iomeval/extract.py
iomeval/mapper.py
iomeval/pipeline.py
iomeval/readers.py
iomeval/themes.py
iomeval/files/prompts/gcm.md
iomeval/files/prompts/select_sections.md
iomeval/files/prompts/srf_ccps.md
iomeval/files/prompts/srf_enablers.md
iomeval/files/prompts/srf_outputs.md
iomeval/files/themes/crosscutting_priorities.json
iomeval/files/themes/gcm_to_srf_outputs.json
iomeval/files/themes/gcms_long.md
iomeval/files/themes/gcms_short.md
iomeval/files/themes/srf_enablers.json
iomeval/files/themes/srf_objectives.json
iomeval/files/themes/srf_outputs_to_gcm.json
iomeval-0.1.7.dist-info/licenses/LICENSE
iomeval-0.1.7.dist-info/METADATA
iomeval-0.1.7.dist-info/WHEEL
iomeval-0.1.7.dist-info/entry_points.txt
iomeval-0.1.7.dist-info/top_level.txt
iomeval-0.1.7.dist-info/RECORD
